README.rst
setup.py
doodle_dashboard_display.egg-info/PKG-INFO
doodle_dashboard_display.egg-info/SOURCES.txt
doodle_dashboard_display.egg-info/dependency_links.txt
doodle_dashboard_display.egg-info/top_level.txt
doodledashboarddisplay/__about__.py
doodledashboarddisplay/__init__.py
doodledashboarddisplay/display.py