Metadata-Version: 1.2
Name: doodle-dashboard-display
Version: 0.0.8
Summary: Library for building new displays for Doodle-Dashboard.
Home-page: https://github.com/SketchingDev/Doodle-Dashboard-Display
Author: UNKNOWN
Author-email: UNKNOWN
License: MIT
Platform: UNKNOWN
Classifier: Development Status :: 3 - Alpha
Classifier: Programming Language :: Python :: 3.4
Requires-Python: >=3.4
